django_geomultiplechoice/__init__.py
django_geomultiplechoice/admin.py
django_geomultiplechoice/apps.py
django_geomultiplechoice/widgets.py
django_geomultiplechoice/templates/geomultiplechoice_widget.html
django_geomultiplechoice-0.0.5.dist-info/LICENSE
django_geomultiplechoice-0.0.5.dist-info/METADATA
django_geomultiplechoice-0.0.5.dist-info/WHEEL
django_geomultiplechoice-0.0.5.dist-info/top_level.txt
django_geomultiplechoice-0.0.5.dist-info/RECORD
