Metadata-Version: 2.1
Name: django-geomultiplechoice
Version: 0.0.5
Summary: A Django widget to select multiple geographic areas
Home-page: https://github.com/datamade//django-geomultiplechoice
Author: Bea Malsky
Author-email: beamalsky@datamade.us
License: UNKNOWN
Platform: UNKNOWN
Classifier: Programming Language :: Python :: 3
Classifier: License :: OSI Approved :: MIT License
Classifier: Operating System :: OS Independent
Requires-Python: >=3.5
